countries_info/__init__.py
countries_info_mg-1.0.0.dist-info/METADATA
countries_info_mg-1.0.0.dist-info/WHEEL
countries_info_mg-1.0.0.dist-info/top_level.txt
countries_info_mg-1.0.0.dist-info/RECORD
