Metadata-Version: 2.1
Name: countries-info-mg
Version: 1.0.0
Summary: A comprehensive Python library for accessing detailed country information
Home-page: https://github.com/MohanedGhawar2019/countries-info
Author: MohaNed Ghawar
Author-email: mohaned.ghawar@gmail.com
Classifier: Programming Language :: Python :: 3
Classifier: License :: OSI Approved :: MIT License
Classifier: Operating System :: OS Independent
Requires-Python: >=3.6
